x_transformers/__init__.py
x_transformers/attend.py
x_transformers/autoregressive_wrapper.py
x_transformers/belief_state_wrapper.py
x_transformers/continuous.py
x_transformers/dpo.py
x_transformers/entropy_based_tokenizer.py
x_transformers/free_transformer.py
x_transformers/gpt_vae.py
x_transformers/multi_input.py
x_transformers/neo_mlp.py
x_transformers/nonautoregressive_wrapper.py
x_transformers/up_wrapper.py
x_transformers/x_transformers.py
x_transformers/xl_autoregressive_wrapper.py
x_transformers/xval.py
x_transformers-2.14.2.dist-info/METADATA
x_transformers-2.14.2.dist-info/WHEEL
x_transformers-2.14.2.dist-info/licenses/LICENSE
x_transformers-2.14.2.dist-info/RECORD
