Metadata-Version: 2.4
Name: x-transformers
Version: 2.14.2
Summary: X-Transformers
Project-URL: Homepage, https://pypi.org/project/x-transformers/
Project-URL: Repository, https://github.com/lucidrains/x-transformers
Author-email: Phil Wang <lucidrains@gmail.com>
License: MIT License
License-File: LICENSE
Keywords: artificial intelligence,attention mechanism,transformers
Classifier: Development Status :: 4 - Beta
Classifier: Intended Audience :: Developers
Classifier: License :: OSI Approved :: MIT License
Classifier: Programming Language :: Python :: 3.6
Classifier: Topic :: Scientific/Engineering :: Artificial Intelligence
Requires-Python: >=3.9
Requires-Dist: einops>=0.8.0
Requires-Dist: einx>=0.3.0
Requires-Dist: loguru
Requires-Dist: packaging>=21.0
Requires-Dist: torch>=2.0
Provides-Extra: examples
Requires-Dist: adam-atan2-pytorch>=0.2.2; extra == 'examples'
Requires-Dist: lion-pytorch; extra == 'examples'
Requires-Dist: tqdm; extra == 'examples'
Provides-Extra: test
Requires-Dist: pytest; extra == 'test'
